{
  "openIssues": 1,
  "issuesClosedLastHour": 0,
  "issuesClosedLastDay": 5,
  "openPRs": 0,
  "prDetails": [],
  "diffMinutes": 119,
  "diffMinutesMain": 439,
  "commitsLastHour": 0,
  "commitsLastDay": 21,
  "lastFiveCommitMessages": [
    {
      "time": "12:41",
      "message": "1.4.1-0"
    },
    {
      "time": "12:41",
      "message": "1.4.0"
    },
    {
      "time": "12:40",
      "message": "Remove outdated getVersion test from main.test.js\n\nThe getVersio..."
    },
    {
      "time": "12:32",
      "message": "Update from agentic-lib"
    },
    {
      "time": "12:30",
      "message": "Update project version to 1.3.4-0\n\nBumped the version in `packag..."
    }
  ],
  "branches": {
    "count": 0,
    "details": []
  },
  "averagePRAge": 0,
  "testStatus": "PASS",
  "testsLastPassedMinutes": 15,
  "generatedAt": "2025-04-05T20:01:30.780Z"
}