{
  "openIssues": 100,
  "issuesClosedLastHour": 2,
  "issuesClosedLastDay": 63,
  "openPRs": 0,
  "prDetails": [],
  "diffMinutes": 9,
  "diffMinutesMain": 9,
  "commitsLastHour": 6,
  "commitsLastDay": 100,
  "lastFiveCommitMessages": [
    {
      "time": "10:08",
      "message": "Maintain CHAT_API"
    },
    {
      "time": "09:56",
      "message": "Maintain CHAT_API"
    },
    {
      "time": "09:48",
      "message": "Maintain NOTES_MANAGER"
    },
    {
      "time": "09:44",
      "message": "Implemented --toggle-allow-nan command to toggle ALLOW_NAN at ru..."
    },
    {
      "time": "09:38",
      "message": "Maintain HISTORY_LOG"
    }
  ],
  "branches": {
    "count": 1,
    "details": [
      {
        "branch": "agentic-lib-issue-946",
        "minutesSinceLastCommit": 12
      }
    ]
  },
  "averagePRAge": 0,
  "testStatus": "PASS",
  "testsLastPassedMinutes": 15,
  "generatedAt": "2025-04-09T10:18:53.516Z"
}